Workbook

Sheet Дашборд
A1: Дашборд канала
A2: Все цифры здесь — формулы, которые тянут данные с других листов. Ничего не вводите вручную, кроме B13.
A4: Текущие подписчики | B4: =IFERROR(INDEX(Метрики!B5:B1000,COUNT(Метрики!B5:B1000)),0)
A5: Подписчики на старте отслеживания | B5: =IFERROR(INDEX(Метрики!B5:B1000,1),0)
A6: Прирост подписчиков за всё время | B6: =B4-B5
A7: Постов опубликовано всего | B7: =SUM(Метрики!D5:D1000)
A8: Рекламных размещений всего | B8: =COUNTA(Продажи_рекламы!B5:B1000)
A9: Выручка с рекламы (кроме отменённых) | B9: =SUMIFS(Продажи_рекламы!E5:E1000,Продажи_рекламы!J5:J1000,"<>Отменено")
A10: Потрачено на закупы всего | B10: =SUM(Закупы!D5:D1000)
A11: Баланс: реклама − закупы | B11: =B9-B10
A12: Средняя цена подписчика (закупы) | B12: =IFERROR(B10/SUM(Закупы!F5:F1000),0)
A13: Сколько месяцев отслеживаете (для ARPU) | B13: 1
A14: ARPU с подписчика в месяц (реклама) | B14: =IFERROR(B9/B4/B13,0)
A16: Как это использовать:
A17: 1. Заполняйте лист Метрики раз в день (дата + подписчики + посты).
A18: 2. Заполняйте лист Закупы каждый раз, когда покупаете рекламу для роста канала.
A19: 3. Заполняйте лист Продажи_рекламы каждый раз, когда бронируете рекламу в своём канале.
A20: 4. Этот лист посчитает всё сам — открывайте раз в неделю перед отчётом.
A23: Легенда:
A24: Синий текст — заполняете вы
A25: Чёрный текст — формула, не редактировать
A26: Голубая заливка строки — пример для формата

Sheet Метрики
A1: Метрики канала
A2: Заполняйте раз в день (вручную или через digest_bot: python cli.py collect-metrics)
A4: Дата | B4: Подписчики | C4: Прирост за день | D4: Постов опубликовано | E4: Ср. охват поста (24ч) | F4: ERR, % | G4: Заметки
A5: 46285 | B5: 1000 | D5: 1 | E5: 320 | F5: =IFERROR(E5/B5,0) | G5: пример — можно удалить
A6: 46286 | B6: 1012 | C6: =B6-B5 | D6: 2 | E6: 340 | F6: =IFERROR(E6/B6,0)
A7: 46286 | B7: 2 | C7: =IF(B7="","",IFERROR(B7-B6,"")) | D7: 1 | F7: =IFERROR(E7/B7,"")
C8: =IF(B8="","",IFERROR(B8-B7,"")) | F8: =IFERROR(E8/B8,"")
C9: =IF(B9="","",IFERROR(B9-B8,"")) | F9: =IFERROR(E9/B9,"")
C10: =IF(B10="","",IFERROR(B10-B9,"")) | F10: =IFERROR(E10/B10,"")
C11: =IF(B11="","",IFERROR(B11-B10,"")) | F11: =IFERROR(E11/B11,"")
C12: =IF(B12="","",IFERROR(B12-B11,"")) | F12: =IFERROR(E12/B12,"")
C13: =IF(B13="","",IFERROR(B13-B12,"")) | F13: =IFERROR(E13/B13,"")
C14: =IF(B14="","",IFERROR(B14-B13,"")) | F14: =IFERROR(E14/B14,"")
C15: =IF(B15="","",IFERROR(B15-B14,"")) | F15: =IFERROR(E15/B15,"")
C16: =IF(B16="","",IFERROR(B16-B15,"")) | F16: =IFERROR(E16/B16,"")
C17: =IF(B17="","",IFERROR(B17-B16,"")) | F17: =IFERROR(E17/B17,"")
C18: =IF(B18="","",IFERROR(B18-B17,"")) | F18: =IFERROR(E18/B18,"")
C19: =IF(B19="","",IFERROR(B19-B18,"")) | F19: =IFERROR(E19/B19,"")
... C206: =IF(B206="","",IFERROR(B206-B205,"")) | F206: =IFERROR(E206/B206,"")
A208: Допущение: ERR = охват поста / подписчики на дату. Считается по последнему посту дня, а не по среднему за все посты — если постов несколько, посчитайте среднее сами в колонке E.

Sheet Закупы
A1: Закупы (продвижение канала)
A2: Реклама, которую покупаете вы — посевы, Telegram Ads, взаимопиар
A4: Дата | B4: Площадка / канал | C4: Формат | D4: Стоимость | E4: Валюта | F4: Новых подписчиков | G4: Цена подписчика | H4: Окупаемость, мес. | I4: Комментарий
A5: 46283 | B5: @example_channel | C5: Посев | D5: 25000 | E5: RUB | F5: 180 | G5: =IFERROR(D5/F5,0) | H5: =IFERROR(G5/Дашборд!$B$14,0) | I5: пример — можно удалить
G6: =IFERROR(D6/F6,"") | H6: =IFERROR(G6/Дашборд!$B$14,"")
G7: =IFERROR(D7/F7,"") | H7: =IFERROR(G7/Дашборд!$B$14,"")
G8: =IFERROR(D8/F8,"") | H8: =IFERROR(G8/Дашборд!$B$14,"")
G9: =IFERROR(D9/F9,"") | H9: =IFERROR(G9/Дашборд!$B$14,"")
G10: =IFERROR(D10/F10,"") | H10: =IFERROR(G10/Дашборд!$B$14,"")
G11: =IFERROR(D11/F11,"") | H11: =IFERROR(G11/Дашборд!$B$14,"")
G12: =IFERROR(D12/F12,"") | H12: =IFERROR(G12/Дашборд!$B$14,"")
G13: =IFERROR(D13/F13,"") | H13: =IFERROR(G13/Дашборд!$B$14,"")
G14: =IFERROR(D14/F14,"") | H14: =IFERROR(G14/Дашборд!$B$14,"")
G15: =IFERROR(D15/F15,"") | H15: =IFERROR(G15/Дашборд!$B$14,"")
G16: =IFERROR(D16/F16,"") | H16: =IFERROR(G16/Дашборд!$B$14,"")
G17: =IFERROR(D17/F17,"") | H17: =IFERROR(G17/Дашборд!$B$14,"")
... G204: =IFERROR(D204/F204,"") | H204: =IFERROR(G204/Дашборд!$B$14,"")
A206: Окупаемость = цена подписчика / ARPU в месяц (лист Дашборд, ячейка B14). Пока в Дашборд нет данных о доходе, колонка будет пустой/0 — это ожидаемо на старте.

Sheet Продажи_рекламы
A1: Продажи рекламы (в своём канале)
A2: Статус: Забронировано / Опубликовано / Снято / Оплачено / Отменено
A4: Дата размещения | B4: Рекламодатель | C4: Контакт | D4: Формат | E4: Цена | F4: Валюта | G4: Просмотры факт | H4: CPM факт | I4: ERID | J4: Статус | K4: Комментарий
A5: 46288 | B5: Acme Software | C5: @acme_manager | D5: Пост 24ч | E5: 150 | F5: USD | H5: =IFERROR(E5/G5*1000,"") | I5: 2Vtzqv... | J5: Забронировано | K5: пример — можно удалить
H6: =IFERROR(E6/G6*1000,"")
H7: =IFERROR(E7/G7*1000,"")
H8: =IFERROR(E8/G8*1000,"")
H9: =IFERROR(E9/G9*1000,"")
H10: =IFERROR(E10/G10*1000,"")
H11: =IFERROR(E11/G11*1000,"")
H12: =IFERROR(E12/G12*1000,"")
H13: =IFERROR(E13/G13*1000,"")
H14: =IFERROR(E14/G14*1000,"")
H15: =IFERROR(E15/G15*1000,"")
H16: =IFERROR(E16/G16*1000,"")
H17: =IFERROR(E17/G17*1000,"")
... H204: =IFERROR(E204/G204*1000,"")
